nd_metrics
