Metadata-Version: 2.1
Name: nd-metrics
Version: 0.0.8
Summary: Metrics for Author Name Disambiguation (AND) evaluation methods
Home-page: https://github.com/lucianovilasboas/nd_metrics
Author: Luciano Vilas Boas Espiridião
Author-email: lucianovilasboas@gmail.com
License: MIT
Keywords: name disambiguation metrics
Platform: UNKNOWN
Classifier: Programming Language :: Python :: 3
Classifier: License :: OSI Approved :: MIT License
Classifier: Operating System :: OS Independent
Requires-Python: >=3.6
